algorithms/__init__.py
algorithms/ciphers/__init__.py
algorithms/ciphers/caesar_cipher.py
algorithms/ciphers/morse_cipher.py
algorithms/ciphers/README.md
algorithms/ciphers/swap_cipher.py
algorithms/geometric_properties/__init__.py
algorithms/geometric_properties/is_point_on_segment.py
algorithms/geometric_properties/point_position.py
algorithms/geometric_properties/README.md
algorithms/geometric_properties/triangle_properties.py
algorithms/integers/__init__.py
algorithms/integers/euclidean_algorithm.py
algorithms/integers/fibonacci.py
algorithms/integers/number.py
algorithms/integers/README.md
algorithms/numerical/__init__.py
algorithms/numerical/bisection_root_finding.py
algorithms/numerical/fast_exponentiation.py
algorithms/numerical/horner.py
algorithms/numerical/README.md
algorithms/numerical/rectangular_integration.py
algorithms/numerical/square_root.py
algorithms/numerical/trapezoid_integration.py
algorithms/sorting/__init__.py
algorithms/sorting/binary_sort.py
algorithms/sorting/bubble_sort.py
algorithms/sorting/insert_sort.py
algorithms/sorting/quick_sort.py
algorithms/sorting/README.md
algorithms/sorting/selection_sort.py
algorithms/strings/__init__.py
algorithms/strings/README.md
algorithms/strings/string_operations.py
python_algorithms_adrianfr-0.1.0.dist-info/METADATA
python_algorithms_adrianfr-0.1.0.dist-info/WHEEL
python_algorithms_adrianfr-0.1.0.dist-info/RECORD
