Metadata-Version: 2.1
Name: python_algorithms_adrianfr
Version: 0.1.0
Summary: A project with simple Python algorithms
License: MIT
Author: Adrian Frączek
Author-email: adrian.fra97@gmail.com
Requires-Python: >=3.12,<4.0
Classifier: License :: OSI Approved :: MIT License
Classifier: Programming Language :: Python :: 3
Classifier: Programming Language :: Python :: 3.12
